urgxy_env/__init__.py
urgxy_env/envs/__init__.py
urgxy_env/envs/env_urgxy.py
urgxy_env-0.2.0.dist-info/METADATA
urgxy_env-0.2.0.dist-info/WHEEL
urgxy_env-0.2.0.dist-info/top_level.txt
urgxy_env-0.2.0.dist-info/RECORD
