Metadata-Version: 2.1
Name: urgxy-env
Version: 0.2.0
Summary: An OpenAI Gym Env for dual UR5
Author: GXY
Requires-Python: >=3.6
Requires-Dist: gym
Requires-Dist: pybullet
Requires-Dist: numpy
